MANIFEST.in
README.rst
setup.py
django_ponydebugger/__init__.py
django_ponydebugger/client.py
django_ponydebugger/django-icon.png
django_ponydebugger/exceptions.py
django_ponydebugger/middleware.py
django_ponydebugger.egg-info/PKG-INFO
django_ponydebugger.egg-info/SOURCES.txt
django_ponydebugger.egg-info/dependency_links.txt
django_ponydebugger.egg-info/requires.txt
django_ponydebugger.egg-info/top_level.txt
django_ponydebugger/domains/__init__.py
django_ponydebugger/domains/base.py
django_ponydebugger/domains/console.py
django_ponydebugger/domains/network.py
django_ponydebugger/domains/runtime.py