Metadata-Version: 1.1
Name: django-ponydebugger
Version: 0.0.3
Summary: PonyDebugger support for Django
Home-page: https://github.com/educreations/django-ponydebugger
Author: Matthew Eastman
Author-email: matt@educreations.com
License: MIT
Platform: UNKNOWN
Classifier: Environment :: Web Environment
Classifier: Framework :: Django
Classifier: Intended Audience :: Developers
Classifier: License :: OSI Approved :: MIT License
Classifier: Topic :: Software Development :: Debuggers
